hooks/__init__.py
hooks/runlayer-hook.sh
runlayer_cli/__init__.py
runlayer_cli/api.py
runlayer_cli/config.py
runlayer_cli/env_substitution.py
runlayer_cli/index.html
runlayer_cli/logging.py
runlayer_cli/main.py
runlayer_cli/middleware.py
runlayer_cli/models.py
runlayer_cli/oauth.py
runlayer_cli/oauth_callback.py
runlayer_cli/paths.py
runlayer_cli/commands/__init__.py
runlayer_cli/commands/auth.py
runlayer_cli/commands/cache.py
runlayer_cli/commands/deploy.py
runlayer_cli/commands/scan.py
runlayer_cli/commands/setup.py
runlayer_cli/deploy/__init__.py
runlayer_cli/deploy/config.py
runlayer_cli/deploy/docker_builder.py
runlayer_cli/deploy/service.py
runlayer_cli/scan/__init__.py
runlayer_cli/scan/clients.py
runlayer_cli/scan/config_parser.py
runlayer_cli/scan/device.py
runlayer_cli/scan/project_scanner.py
runlayer_cli/scan/service.py
runlayer_cli/verified_local_proxy/README.md
runlayer_cli/verified_local_proxy/__init__.py
runlayer_cli/verified_local_proxy/config.py
runlayer_cli/verified_local_proxy/exceptions.py
runlayer_cli/verified_local_proxy/proxy.py
runlayer_cli/verified_local_proxy/verification/__init__.py
runlayer_cli/verified_local_proxy/verification/base.py
runlayer_cli/verified_local_proxy/verification/macos.py
runlayer_cli/verified_local_proxy/verification/windows.py
runlayer-0.12.2.dist-info/METADATA
runlayer-0.12.2.dist-info/WHEEL
runlayer-0.12.2.dist-info/entry_points.txt
runlayer-0.12.2.dist-info/licenses/LICENSE
runlayer-0.12.2.dist-info/RECORD
