Metadata-Version: 2.4
Name: runlayer
Version: 0.12.2
Summary: A command-line interface for running MCP servers via HTTP transport
Project-URL: Homepage, https://runlayer.com
Project-URL: Documentation, https://docs.runlayer.com/
Author-email: Runlayer <engineering@runlayer.com>
License:                                  Apache License
License-File: LICENSE
Keywords: agent,anysource,cli,llm,mcp,runlayer
Classifier: Intended Audience :: Developers
Classifier: License :: OSI Approved :: Apache Software License
Classifier: Programming Language :: Python :: 3
Classifier: Programming Language :: Python :: 3.10
Classifier: Programming Language :: Python :: 3.11
Classifier: Programming Language :: Python :: 3.12
Classifier: Programming Language :: Python :: 3.13
Classifier: Topic :: Internet :: WWW/HTTP
Classifier: Topic :: Software Development :: Libraries :: Python Modules
Requires-Python: >=3.10
Requires-Dist: docker>=7.0.0
Requires-Dist: fastmcp>=2.12.3
Requires-Dist: httpx>=0.27.0
Requires-Dist: json5>=0.12.1
Requires-Dist: mcp>=1.0.0
Requires-Dist: python-dotenv>=1.0.0
Requires-Dist: pyyaml>=6.0.0
Requires-Dist: rich>=13.0.0
Requires-Dist: structlog>=25.4.0
Requires-Dist: typer>=0.17.4
